<?xml version="1.0" encoding="utf-8"?>
<!DOCTYPE hibernate-mapping PUBLIC "-//Hibernate/Hibernate Mapping DTD 3.0//EN"
"http://hibernate.sourceforge.net/hibernate-mapping-3.0.dtd">
<!-- 
    Mapping file autogenerated by MyEclipse Persistence Tools
-->
<hibernate-mapping>
    <class name="com.nsc.dem.bean.system.TTreeDef" table="T_TREE_DEF" schema="EDM">
        <id name="id" type="java.lang.Long">
            <column name="ID" precision="10" scale="0" />
            <generator class="sequence">  
			<param name="sequence">SEQ_T_TREE_DEF</param>  
			</generator>
        </id>
        <many-to-one name="TUser" class="com.nsc.dem.bean.profile.TUser" fetch="select">
            <column name="CREATOR" length="25" not-null="true" />
        </many-to-one>
        <many-to-one name="TNodeDef" class="com.nsc.dem.bean.system.TNodeDef" fetch="select" lazy="false">
            <column name="NODE_DEF_ID" precision="10" scale="0" not-null="true" />
        </many-to-one>
        <property name="name" type="java.lang.String">
            <column name="NAME" length="10" not-null="false" />
        </property>
        <property name="remark" type="java.lang.String">
            <column name="REMARK" />
        </property>
        <property name="imageUrl" type="java.lang.String">
            <column name="IMAGE_URL" />
        </property>
        <property name="createDate" type="java.util.Date">
            <column name="CREATE_DATE" length="7" not-null="true" />
        </property>
        <property name="parentId" type="java.lang.Long">
            <column name="PARENT_ID" precision="10" scale="0" not-null="true" />
        </property>
        <set name="TRoleTrees" inverse="true">
            <key>
                <column name="TREE_ID" precision="10" scale="0" not-null="true" />
            </key>
            <one-to-many class="com.nsc.dem.bean.system.TRoleTree" />
        </set>
    </class>
</hibernate-mapping>
